<?xml version="1.0" encoding="utf-8"?>
<hosts xmlns:xsi="http://www.w3.org/2001/XMLSchema-instance" xmlns:xsd="http://www.w3.org/2001/XMLSchema">
  <host name="My Kodi" port="80" username="kodi" address="Kodi IP" password="" remotepathseparator="/" realtimesync="true">
    <source>
      <type>movie</type>
      <remotepath>- Please Populate Sources! -</remotepath>
      <applicationpath>-</applicationpath>
    </source>
    <source>
      <type>tvshow</type>
      <remotepath>- Please Populate Sources! -</remotepath>
      <applicationpath>-</applicationpath>
    </source>
  </host>
</hosts>