<?xml version="1.0" encoding="utf-8"?>
<!--
### Anchor Help ###
0 = none
1 = Top
2 = Bottom
4 = Left
8 = Right

Can be combined by adding values. For example, the standard TopLeft anchor would
be anchor code 5.

### FontStyle Help ###
0 = Regular
1 = Bold
2 = Italic
4 = Underline
8 = Strikeout

Can be combined by adding values. For example, bold and underlined would be
fontstyle code 5.

### Color Help ###
Color can be a "system-defined color" https://msdn.microsoft.com/en-us/library/system.drawing.knowncolor%28v=vs.110%29.aspx
or a "32-bit ARGB value"
-->

<theme>
  <filterpanel>
    <backcolor>Control</backcolor>
    <button>
      <forecolor>ControlText</forecolor>
    </button>
    <forecolor>ControlText</forecolor>
    <header>
      <backcolor>ControlDarkDark</backcolor>
      <forecolor>HighlightText</forecolor>
    </header>
  </filterpanel>

  <imagepanel>
    <backcolor>Gainsboro</backcolor>
    <forecolor>Black</forecolor>
    <mpaa>
      <backcolor>Gainsboro</backcolor>
    </mpaa>
    <imagename>
      <backcolor>DimGray</backcolor>
      <forecolor>HighlightText</forecolor>
    </imagename>
    <imagesize>
      <backcolor>DimGray</backcolor>
      <forecolor>HighlightText</forecolor>
    </imagesize>
    <fanartsmall>
      <left>299</left>
      <maxheight>160</maxheight>
      <maxwidth>285</maxwidth>
      <top>130</top>
    </fanartsmall>
    <poster>
      <left>4</left>
      <maxheight>160</maxheight>
      <maxwidth>285</maxwidth>
      <top>130</top>
    </poster>
  </imagepanel>

  <infopanel>
    <backcolor>Gainsboro</backcolor>
    <posmid>280</posmid>
    <!-- Must be a multiple of 5!! -->
    <posup>280</posup>
    <!-- Must be a multiple of 5!! -->

    <control name="lblInfoPanelHeader">
      <anchor>13</anchor>
      <backcolor>ControlDarkDark</backcolor>
      <font>Microsoft Sans Serif</font>
      <fontsize>8</fontsize>
      <fontstyle>1</fontstyle>
      <forecolor>-1</forecolor>
      <height>17</height>
      <left>3</left>
      <top>3</top>
      <width>pnlInfoPanel.Width - 8</width>
    </control>

    <control name="btnUp">
      <anchor>9</anchor>
      <height>22</height>
      <left>pnlInfoPanel.Width - 71</left>
      <top>1</top>
      <width>30</width>
    </control>

    <control name="btnDown">
      <anchor>9</anchor>
      <height>22</height>
      <left>pnlInfoPanel.Width - 38</left>
      <top>1</top>
      <width>30</width>
    </control>

    <control name="pnlActors">
      <anchor>9</anchor>
      <backcolor>Gainsboro</backcolor>
      <height>244</height>
      <left>pnlInfoPanel.Width - 505</left>
      <top>27</top>
      <width>302</width>
    </control>

    <!-- BEGIN INTERNAL OF PNLACTORS -->
    <control name="lblActorsHeader">
      <anchor>5</anchor>
      <backcolor>ControlDarkDark</backcolor>
      <font>Microsoft Sans Serif</font>
      <fontsize>8</fontsize>
      <fontstyle>1</fontstyle>
      <forecolor>-1</forecolor>
      <height>17</height>
      <left>0</left>
      <top>0</top>
      <width>301</width>
    </control>

    <control name="lstActors">
      <anchor>5</anchor>
      <backcolor>Gainsboro</backcolor>
      <font>Microsoft Sans Serif</font>
      <fontsize>8</fontsize>
      <fontstyle>0</fontstyle>
      <forecolor>Black</forecolor>
      <height>221</height>
      <left>3</left>
      <top>21</top>
      <width>214</width>
    </control>

    <control name="pbActors">
      <anchor>5</anchor>
      <backcolor>Gainsboro</backcolor>
      <height>106</height>
      <left>220</left>
      <top>75</top>
      <width>81</width>
    </control>

    <control name="pbActLoad">
      <anchor>5</anchor>
      <backcolor>Gainsboro</backcolor>
      <height>39</height>
      <left>240</left>
      <top>111</top>
      <width>41</width>
    </control>
    <!-- END INTERNAL OF PNLACTORS -->

    <control name="lblMetaDataHeader">
      <anchor>9</anchor>
      <backcolor>ControlDarkDark</backcolor>
      <font>Microsoft Sans Serif</font>
      <fontsize>8</fontsize>
      <fontstyle>1</fontstyle>
      <forecolor>-1</forecolor>
      <height>17</height>
      <left>pnlInfoPanel.Width - 200</left>
      <top>27</top>
      <width>195</width>
    </control>

    <control name="btnMetaDataRefresh">
      <anchor>9</anchor>
      <font>Microsoft Sans Serif</font>
      <fontsize>8</fontsize>
      <fontstyle>0</fontstyle>
      <height>23</height>
      <left>lblMetaDataHeader.Left + 125</left>
      <top>23</top>
      <width>65</width>
    </control>

    <control name="txtMetaData">
      <anchor>9</anchor>
      <backcolor>Gainsboro</backcolor>
      <font>Microsoft Sans Serif</font>
      <fontsize>8</fontsize>
      <fontstyle>0</fontstyle>
      <forecolor>Black</forecolor>
      <height>221</height>
      <left>lblMetaDataHeader.Left</left>
      <top>50</top>
      <width>lblMetaDataHeader.Width</width>
    </control>

    <control name="lblPlotHeader">
      <anchor>13</anchor>
      <backcolor>ControlDarkDark</backcolor>
      <font>Microsoft Sans Serif</font>
      <fontsize>8</fontsize>
      <fontstyle>1</fontstyle>
      <forecolor>-1</forecolor>
      <height>17</height>
      <left>3</left>
      <top>81</top>
      <width>pnlInfoPanel.Width - 511</width>
    </control>

    <control name="txtPlot">
      <anchor>13</anchor>
      <backcolor>Gainsboro</backcolor>
      <font>Microsoft Sans Serif</font>
      <fontsize>8</fontsize>
      <fontstyle>0</fontstyle>
      <forecolor>Black</forecolor>
      <height>78</height>
      <left>3</left>
      <top>103</top>
      <width>lblPlotHeader.Width</width>
    </control>

    <control name="lblFilePathHeader">
      <anchor>13</anchor>
      <backcolor>ControlDarkDark</backcolor>
      <font>Microsoft Sans Serif</font>
      <fontsize>8</fontsize>
      <fontstyle>1</fontstyle>
      <forecolor>-1</forecolor>
      <height>17</height>
      <left>3</left>
      <top>234</top>
      <width>lblPlotHeader.Width</width>
    </control>

    <control name="txtFilePath">
      <anchor>13</anchor>
      <backcolor>-1</backcolor>
      <font>Microsoft Sans Serif</font>
      <fontsize>8</fontsize>
      <fontstyle>0</fontstyle>
      <forecolor>Black</forecolor>
      <height>20</height>
      <left>3</left>
      <top>254</top>
      <width>lblFilePathHeader.Width - 23</width>
    </control>

    <control name="btnFilePlay">
      <anchor>9</anchor>
      <height>20</height>
      <left>txtFilePath.Width + 6</left>
      <top>254</top>
      <width>20</width>
    </control>

    <control name="lblIMDBHeader">
      <anchor>5</anchor>
      <backcolor>ControlDarkDark</backcolor>
      <font>Microsoft Sans Serif</font>
      <fontsize>8</fontsize>
      <fontstyle>1</fontstyle>
      <forecolor>-1</forecolor>
      <height>17</height>
      <left>3</left>
      <top>188</top>
      <width>108</width>
    </control>

    <control name="txtIMDBID">
      <anchor>5</anchor>
      <backcolor>-1</backcolor>
      <font>Microsoft Sans Serif</font>
      <fontsize>8</fontsize>
      <fontstyle>0</fontstyle>
      <forecolor>Black</forecolor>
      <height>20</height>
      <left>3</left>
      <top>208</top>
      <width>108</width>
    </control>

    <control name="lblTMDBHeader">
      <anchor>5</anchor>
      <backcolor>ControlDarkDark</backcolor>
      <font>Microsoft Sans Serif</font>
      <fontsize>8</fontsize>
      <fontstyle>1</fontstyle>
      <forecolor>-1</forecolor>
      <height>17</height>
      <left>117</left>
      <top>188</top>
      <width>108</width>
    </control>

    <control name="txtTMDBID">
      <anchor>5</anchor>
      <backcolor>-1</backcolor>
      <font>Microsoft Sans Serif</font>
      <fontsize>8</fontsize>
      <fontstyle>0</fontstyle>
      <forecolor>Black</forecolor>
      <height>20</height>
      <left>117</left>
      <top>208</top>
      <width>108</width>
    </control>

    <control name="lblTVDBHeader">
      <anchor>5</anchor>
      <backcolor>ControlDarkDark</backcolor>
      <font>Microsoft Sans Serif</font>
      <fontsize>8</fontsize>
      <fontstyle>1</fontstyle>
      <forecolor>-1</forecolor>
      <height>17</height>
      <left>231</left>
      <top>188</top>
      <width>108</width>
    </control>

    <control name="txtTVDBID">
      <anchor>5</anchor>
      <backcolor>-1</backcolor>
      <font>Microsoft Sans Serif</font>
      <fontsize>8</fontsize>
      <fontstyle>0</fontstyle>
      <forecolor>Black</forecolor>
      <height>20</height>
      <left>231</left>
      <top>208</top>
      <width>108</width>
    </control>

    <control name="lblDirectorsHeader">
      <anchor>5</anchor>
      <backcolor>ControlDarkDark</backcolor>
      <font>Microsoft Sans Serif</font>
      <fontsize>8</fontsize>
      <fontstyle>1</fontstyle>
      <forecolor>-1</forecolor>
      <height>17</height>
      <left>3</left>
      <top>27</top>
      <width>300</width>
    </control>

    <control name="lblDirectors">
      <anchor>5</anchor>
      <backcolor>Gainsboro</backcolor>
      <font>Microsoft Sans Serif</font>
      <fontsize>8</fontsize>
      <fontstyle>0</fontstyle>
      <forecolor>Black</forecolor>
      <height>16</height>
      <left>3</left>
      <top>48</top>
      <width>lblDirectorsHeader.Width</width>
    </control>

    <control name="lblCreditsHeader">
      <anchor>13</anchor>
      <backcolor>ControlDarkDark</backcolor>
      <font>Microsoft Sans Serif</font>
      <fontsize>8</fontsize>
      <fontstyle>1</fontstyle>
      <forecolor>-1</forecolor>
      <height>17</height>
      <left>310</left>
      <top>27</top>
      <width>pnlInfoPanel.Width - 818</width>
    </control>

    <control name="lblCredits">
      <anchor>13</anchor>
      <backcolor>Gainsboro</backcolor>
      <font>Microsoft Sans Serif</font>
      <fontsize>8</fontsize>
      <fontstyle>0</fontstyle>
      <forecolor>Black</forecolor>
      <height>16</height>
      <left>310</left>
      <top>48</top>
      <width>lblCreditsHeader.Width</width>
    </control>
  </infopanel>

  <medialist>
    <backcolor>White</backcolor>
    <default>
      <backcolor>White</backcolor>
      <forecolor>Black</forecolor>
      <selectionbackcolor>Highlight</selectionbackcolor>
      <selectionforecolor>HighlightText</selectionforecolor>
    </default>
    <locked>
      <backcolor>LightSteelBlue</backcolor>
      <forecolor>Black</forecolor>
      <selectionbackcolor>DarkTurquoise</selectionbackcolor>
      <selectionforecolor>Black</selectionforecolor>
    </locked>
    <marked>
      <backcolor>White</backcolor>
      <forecolor>Crimson</forecolor>
      <selectionbackcolor>Highlight</selectionbackcolor>
      <selectionforecolor>Crimson</selectionforecolor>
    </marked>
    <missing>
      <backcolor>White</backcolor>
      <forecolor>Gray</forecolor>
      <selectionbackcolor>DarkGray</selectionbackcolor>
      <selectionforecolor>LightGray</selectionforecolor>
    </missing>
    <new>
      <backcolor>White</backcolor>
      <forecolor>Green</forecolor>
      <selectionbackcolor>Highlight</selectionbackcolor>
      <selectionforecolor>Green</selectionforecolor>
    </new>
  </medialist>

  <toppanel>
    <backcolor>-2302756</backcolor>
    <originaltitle>
      <backcolor>Gainsboro</backcolor>
      <forecolor>Black</forecolor>
    </originaltitle>
    <rating>
      <backcolor>Gainsboro</backcolor>
      <forecolor>Black</forecolor>
    </rating>
    <runtime>
      <backcolor>Gainsboro</backcolor>
      <forecolor>Black</forecolor>
    </runtime>
    <studio>
      <backcolor>Gainsboro</backcolor>
      <forecolor>Black</forecolor>
    </studio>
    <title>
      <backcolor>Gainsboro</backcolor>
      <forecolor>Black</forecolor>
    </title>
    <tagline>
      <backcolor>Gainsboro</backcolor>
      <forecolor>Black</forecolor>
    </tagline>
  </toppanel>
</theme>